
  [
    {
      "ClientID": "5EE9B5AE-1D0A-41EA-8943-EB52A4C9F20A",
      "ClientName": "Kholoud",
      "Country": "Egypt",
      "Phone": "0100000000",
      "Age": 28,
      "Gender": "female",
      "Notes": "",
      "Email": "kholouddesouky@gmail.com"
    },
    {
      "ClientID": "485621B3-2A44-4D22-A870-EE9CC3F22326",
      "ClientName": "Maha",
      "Country": "USA",
      "Phone": "+12029882614",
      "Age": 36,
      "Gender": "female",
      "Notes": "",
      "Email": "Test@gmail.com"
    },
    {
      "ClientID": "DD651DB5-C90D-4BDA-BAB9-A8E8E83B7DF2",
      "ClientName": "Rania",
      "Country": "Germany",
      "Phone": "+4932211077146",
      "Age": 40,
      "Gender": "female",
      "Notes": "",
      "Email": "Rania@gmail.com"
    }
  ]


